README.md
setup.py
lc_structure/GraphNode.py
lc_structure/ListNode.py
lc_structure/Node.py
lc_structure/TreeNode.py
lc_structure/__init__.py
lc_structure.egg-info/PKG-INFO
lc_structure.egg-info/SOURCES.txt
lc_structure.egg-info/dependency_links.txt
lc_structure.egg-info/top_level.txt