Metadata-Version: 2.1
Name: lc-structure
Version: 0.0.2
Summary: A tool to create linked list, binary tree and graph from array or dictionary for the ease of local test
Home-page: https://github.com/singwai/lc-structure
Author: Singwai Chan
Author-email: c.singwai@gmail.com
License: UNKNOWN
Keywords: LeetCode
Platform: UNKNOWN
Classifier: Programming Language :: Python :: 3
Classifier: Programming Language :: Python :: 3.4
Classifier: Programming Language :: Python :: 3.5
Classifier: Programming Language :: Python :: 3.6
Classifier: License :: OSI Approved :: MIT License
Classifier: Operating System :: OS Independent
